mosaikdemod/__init__.py
mosaikdemod/adaptors.py
mosaikdemod-0.1.post1.dist-info/LICENSE.txt
mosaikdemod-0.1.post1.dist-info/METADATA
mosaikdemod-0.1.post1.dist-info/WHEEL
mosaikdemod-0.1.post1.dist-info/top_level.txt
mosaikdemod-0.1.post1.dist-info/RECORD
