Metadata-Version: 2.1
Name: mosaikdemod
Version: 0.1.post1
Summary: Adaptor to use demod simulators in mosaik.
Home-page: https://github.com/epfl-herus/mosaik-demod
Author: demod-herus
Author-email: demod@groupes.epfl.ch
License: UNKNOWN
Project-URL: Documentation, https://demod.readthedocs.io/en/latest/tutorials/cosimulation.html#mosaik-integration
Project-URL: demod, https://demod.readthedocs.io/en/latest/index.html
Project-URL: mosaik, https://mosaik.readthedocs.io/en/latest/overview.html
Platform: UNKNOWN
Classifier: Development Status :: 4 - Beta
Classifier: License :: OSI Approved :: GNU General Public License v3 (GPLv3)
Classifier: Programming Language :: Python :: 3
Classifier: Operating System :: OS Independent
Requires-Python: >=3.8
License-File: LICENSE.txt
Requires-Dist: mosaik-api
